odoo/addons/helpdesk_mgmt/README.rst
odoo/addons/helpdesk_mgmt/__init__.py
odoo/addons/helpdesk_mgmt/__manifest__.py
odoo/addons/helpdesk_mgmt/controllers/__init__.py
odoo/addons/helpdesk_mgmt/controllers/main.py
odoo/addons/helpdesk_mgmt/controllers/myaccount.py
odoo/addons/helpdesk_mgmt/data/helpdesk_data.xml
odoo/addons/helpdesk_mgmt/demo/helpdesk_demo.xml
odoo/addons/helpdesk_mgmt/i18n/es.po
odoo/addons/helpdesk_mgmt/i18n/es_AR.po
odoo/addons/helpdesk_mgmt/i18n/fr.po
odoo/addons/helpdesk_mgmt/i18n/helpdesk_mgmt.pot
odoo/addons/helpdesk_mgmt/i18n/hu.po
odoo/addons/helpdesk_mgmt/i18n/it.po
odoo/addons/helpdesk_mgmt/i18n/pt_BR.po
odoo/addons/helpdesk_mgmt/i18n/tr.po
odoo/addons/helpdesk_mgmt/i18n/zh_TW.po
odoo/addons/helpdesk_mgmt/migrations/13.0.1.0.1/post-migrate.py
odoo/addons/helpdesk_mgmt/migrations/13.0.1.14.0/post-migration.py
odoo/addons/helpdesk_mgmt/migrations/13.0.1.2.3/pre-migrate.py
odoo/addons/helpdesk_mgmt/migrations/13.0.1.7.0/post-migration.py
odoo/addons/helpdesk_mgmt/migrations/13.0.1.7.0/pre-migrate.py
odoo/addons/helpdesk_mgmt/migrations/13.0.1.8.1/noupdate_changes.xml
odoo/addons/helpdesk_mgmt/migrations/13.0.1.8.1/post-migration.py
odoo/addons/helpdesk_mgmt/migrations/13.0.2.2.0/noupdate_changes.xml
odoo/addons/helpdesk_mgmt/migrations/13.0.2.2.0/post-migration.py
odoo/addons/helpdesk_mgmt/migrations/13.0.2.5.0/noupdate_changes.xml
odoo/addons/helpdesk_mgmt/migrations/13.0.2.5.0/post-migration.py
odoo/addons/helpdesk_mgmt/models/__init__.py
odoo/addons/helpdesk_mgmt/models/helpdesk_ticket.py
odoo/addons/helpdesk_mgmt/models/helpdesk_ticket_category.py
odoo/addons/helpdesk_mgmt/models/helpdesk_ticket_channel.py
odoo/addons/helpdesk_mgmt/models/helpdesk_ticket_stage.py
odoo/addons/helpdesk_mgmt/models/helpdesk_ticket_tag.py
odoo/addons/helpdesk_mgmt/models/helpdesk_ticket_team.py
odoo/addons/helpdesk_mgmt/models/res_company.py
odoo/addons/helpdesk_mgmt/models/res_config_settings.py
odoo/addons/helpdesk_mgmt/models/res_partner.py
odoo13_addon_helpdesk_mgmt-13.0.2.7.0.dist-info/METADATA
odoo13_addon_helpdesk_mgmt-13.0.2.7.0.dist-info/WHEEL
odoo13_addon_helpdesk_mgmt-13.0.2.7.0.dist-info/top_level.txt
odoo13_addon_helpdesk_mgmt-13.0.2.7.0.dist-info/RECORD
